kqlalchemy/__init__.py
kqlalchemy/kql_dialect.py
kqlalchemy/pyodbc.py
kqlalchemy-0.1.0.dist-info/WHEEL
kqlalchemy-0.1.0.dist-info/METADATA
kqlalchemy-0.1.0.dist-info/LICENSE
kqlalchemy-0.1.0.dist-info/RECORD
